[{"tid": 3734901, "duration": 198, "slot": 3}, {"tid": 5468789, "duration": 256, "slot": 3}, {"tid": 674791, "duration": 205, "slot": 3}, {"tid": 11282737, "duration": 207, "slot": 3}, {"tid": 11092118, "duration": 291, "slot": 3}, {"tid": 576149, "duration": 184, "slot": 3}, {"tid": 613229, "duration": 223, "slot": 3}, {"tid": 727172, "duration": 0, "slot": 3}, {"tid": 11108631, "duration": 253, "slot": 3}, {"tid": 10416309, "duration": 226, "slot": 3}, {"tid": 548365, "duration": 165, "slot": 3}, {"tid": 6719521, "duration": 301, "slot": 3}, {"tid": 2606300, "duration": 228, "slot": 3}, {"tid": 6195606, "duration": 226, "slot": 3}, {"tid": 12996967, "duration": 99, "slot": 3}, {"tid": 10745154, "duration": 212, "slot": 4}, {"tid": 2459666, "duration": 345, "slot": 4}, {"tid": 2335428, "duration": 384, "slot": 4}, {"tid": 12189443, "duration": 411, "slot": 4}, {"tid": 4114329, "duration": 0, "slot": 4}, {"tid": 1921994, "duration": 170, "slot": 4}, {"tid": 674791, "duration": 205, "slot": 4}, {"tid": 10705331, "duration": 375, "slot": 4}, {"tid": 4282199, "duration": 228, "slot": 4}, {"tid": 576149, "duration": 184, "slot": 4}, {"tid": 532923, "duration": 205, "slot": 4}, {"tid": 12189439, "duration": 269, "slot": 4}, {"tid": 4207658, "duration": 65, "slot": 4}, {"tid": 10991506, "duration": 214, "slot": 4}, {"tid": 2172321, "duration": 267, "slot": 4}, {"tid": 2210795, "duration": 255, "slot": 4}, {"tid": 3753097, "duration": 229, "slot": 4}, {"tid": 953326, "duration": 251, "slot": 4}, {"tid": 3110732, "duration": 247, "slot": 4}, {"tid": 9809625, "duration": 235, "slot": 4}, {"tid": 727194, "duration": 0, "slot": 4}, {"tid": 6284343, "duration": 298, "slot": 4}, {"tid": 2335427, "duration": 249, "slot": 4}, {"tid": 11127858, "duration": 445, "slot": 4}, {"tid": 3131211, "duration": 255, "slot": 4}, {"tid": 11127856, "duration": 258, "slot": 4}, {"tid": 10834251, "duration": 228, "slot": 4}, {"tid": 2417152, "duration": 353, "slot": 4}, {"tid": 12687725, "duration": 253, "slot": 4}, {"tid": 6171892, "duration": 218, "slot": 4}, {"tid": 11108621, "duration": 300, "slot": 4}, {"tid": 532923, "duration": 205, "slot": 4}, {"tid": 5468789, "duration": 256, "slot": 4}, {"tid": 4114329, "duration": 0, "slot": 4}, {"tid": 6493413, "duration": 226, "slot": 4}]