[{"tid": 2103143, "duration": 225, "slot": 3}, {"tid": 960487, "duration": 245, "slot": 3}, {"tid": 532237, "duration": 588, "slot": 3}, {"tid": 3127968, "duration": 221, "slot": 3}, {"tid": 1907231, "duration": 232, "slot": 3}, {"tid": 5426878, "duration": 215, "slot": 3}, {"tid": 12335547, "duration": 210, "slot": 3}, {"tid": 3254039, "duration": 195, "slot": 3}, {"tid": 2303731, "duration": 292, "slot": 3}, {"tid": 672910, "duration": 0, "slot": 3}, {"tid": 3127630, "duration": 217, "slot": 3}, {"tid": 870783, "duration": 308, "slot": 3}, {"tid": 533620, "duration": 288, "slot": 3}, {"tid": 3102237, "duration": 214, "slot": 4}, {"tid": 2447245, "duration": 238, "slot": 4}, {"tid": 1174521, "duration": 241, "slot": 4}, {"tid": 1126634, "duration": 288, "slot": 4}, {"tid": 547490, "duration": 283, "slot": 4}, {"tid": 1039149, "duration": 310, "slot": 4}, {"tid": 9806943, "duration": 426, "slot": 4}, {"tid": 568234, "duration": 272, "slot": 4}, {"tid": 1583104, "duration": 256, "slot": 4}, {"tid": 1582530, "duration": 258, "slot": 4}, {"tid": 2673702, "duration": 309, "slot": 4}, {"tid": 1030221, "duration": 224, "slot": 4}, {"tid": 849210, "duration": 294, "slot": 4}, {"tid": 2221502, "duration": 306, "slot": 4}, {"tid": 1117823, "duration": 220, "slot": 4}, {"tid": 774835, "duration": 250, "slot": 4}, {"tid": 2125339, "duration": 249, "slot": 4}, {"tid": 2310282, "duration": 278, "slot": 4}, {"tid": 2504634, "duration": 347, "slot": 4}, {"tid": 960487, "duration": 245, "slot": 4}, {"tid": 1174521, "duration": 241, "slot": 4}, {"tid": 3593271, "duration": 303, "slot": 4}, {"tid": 3254036, "duration": 274, "slot": 4}, {"tid": 541999, "duration": 274, "slot": 4}, {"tid": 3092100, "duration": 228, "slot": 4}, {"tid": 568234, "duration": 272, "slot": 4}, {"tid": 1582530, "duration": 258, "slot": 4}, {"tid": 3177037, "duration": 208, "slot": 4}, {"tid": 859129, "duration": 202, "slot": 4}, {"tid": 547490, "duration": 283, "slot": 4}, {"tid": 3361866, "duration": 350, "slot": 4}, {"tid": 849210, "duration": 294, "slot": 4}, {"tid": 3127968, "duration": 221, "slot": 4}, {"tid": 3042029, "duration": 188, "slot": 4}, {"tid": 2221501, "duration": 304, "slot": 4}, {"tid": 1030832, "duration": 285, "slot": 4}, {"tid": 870783, "duration": 308, "slot": 4}]