[{"tid": 14299590, "duration": 285, "slot": 3}, {"tid": 3089663, "duration": 410, "slot": 3}, {"tid": 3106506, "duration": 311, "slot": 3}, {"tid": 15684447, "duration": 204, "slot": 3}, {"tid": 3153342, "duration": 363, "slot": 3}, {"tid": 3089664, "duration": 300, "slot": 3}, {"tid": 14299593, "duration": 241, "slot": 3}, {"tid": 3098840, "duration": 309, "slot": 3}, {"tid": 15684446, "duration": 285, "slot": 3}, {"tid": 3106502, "duration": 287, "slot": 3}, {"tid": 3423654, "duration": 285, "slot": 3}, {"tid": 15684444, "duration": 245, "slot": 3}, {"tid": 15684355, "duration": 241, "slot": 4}, {"tid": 3098839, "duration": 297, "slot": 4}, {"tid": 3157550, "duration": 271, "slot": 4}, {"tid": 3106504, "duration": 328, "slot": 4}, {"tid": 3157551, "duration": 287, "slot": 4}, {"tid": 12620323, "duration": 210, "slot": 4}, {"tid": 3128095, "duration": 227, "slot": 4}, {"tid": 3142302, "duration": 235, "slot": 4}, {"tid": 15684529, "duration": 245, "slot": 4}, {"tid": 3543965, "duration": 496, "slot": 4}, {"tid": 3157516, "duration": 250, "slot": 4}, {"tid": 3098837, "duration": 318, "slot": 4}, {"tid": 15684447, "duration": 204, "slot": 4}, {"tid": 3089662, "duration": 306, "slot": 4}, {"tid": 14299588, "duration": 242, "slot": 4}, {"tid": 3128093, "duration": 300, "slot": 4}, {"tid": 3157550, "duration": 271, "slot": 4}, {"tid": 15684355, "duration": 241, "slot": 4}, {"tid": 15684350, "duration": 201, "slot": 4}, {"tid": 3157592, "duration": 271, "slot": 4}, {"tid": 3424919, "duration": 169, "slot": 4}, {"tid": 15684445, "duration": 48, "slot": 4}, {"tid": 3098843, "duration": 220, "slot": 4}, {"tid": 3155884, "duration": 218, "slot": 4}, {"tid": 3424921, "duration": 297, "slot": 4}, {"tid": 3157590, "duration": 271, "slot": 4}, {"tid": 3089664, "duration": 300, "slot": 4}, {"tid": 3089663, "duration": 410, "slot": 4}, {"tid": 3119178, "duration": 706, "slot": 4}, {"tid": 3157516, "duration": 250, "slot": 4}, {"tid": 14739187, "duration": 279, "slot": 4}, {"tid": 3089662, "duration": 306, "slot": 4}, {"tid": 49578321, "duration": 239, "slot": 4}, {"tid": 3424946, "duration": 223, "slot": 4}, {"tid": 3106503, "duration": 297, "slot": 4}, {"tid": 3157550, "duration": 271, "slot": 4}, {"tid": 3128096, "duration": 271, "slot": 4}, {"tid": 3142302, "duration": 235, "slot": 4}]