[{"tid": 61167005, "duration": 311, "slot": 3}, {"tid": 63497714, "duration": 231, "slot": 3}, {"tid": 62557258, "duration": 219, "slot": 3}, {"tid": 63453325, "duration": 287, "slot": 3}, {"tid": 64688552, "duration": 209, "slot": 3}, {"tid": 64449028, "duration": 287, "slot": 3}, {"tid": 64404512, "duration": 470, "slot": 3}, {"tid": 64542269, "duration": 204, "slot": 3}, {"tid": 61340077, "duration": 197, "slot": 3}, {"tid": 60852757, "duration": 196, "slot": 3}, {"tid": 63087582, "duration": 269, "slot": 3}, {"tid": 62954000, "duration": 289, "slot": 3}, {"tid": 62978669, "duration": 236, "slot": 4}, {"tid": 64472942, "duration": 292, "slot": 4}, {"tid": 63267303, "duration": 257, "slot": 4}, {"tid": 64014503, "duration": 197, "slot": 4}, {"tid": 63993379, "duration": 171, "slot": 4}, {"tid": 5645692, "duration": 247, "slot": 4}, {"tid": 62557275, "duration": 219, "slot": 4}, {"tid": 63449808, "duration": 248, "slot": 4}, {"tid": 62851106, "duration": 301, "slot": 4}, {"tid": 63461194, "duration": 197, "slot": 4}, {"tid": 64898838, "duration": 288, "slot": 4}, {"tid": 64449028, "duration": 287, "slot": 4}, {"tid": 61228591, "duration": 212, "slot": 4}, {"tid": 64476639, "duration": 219, "slot": 4}, {"tid": 64784398, "duration": 236, "slot": 4}, {"tid": 61167005, "duration": 311, "slot": 4}, {"tid": 63309058, "duration": 208, "slot": 4}, {"tid": 63497714, "duration": 231, "slot": 4}, {"tid": 63226618, "duration": 299, "slot": 4}, {"tid": 63267303, "duration": 257, "slot": 4}, {"tid": 61002680, "duration": 196, "slot": 4}, {"tid": 64404512, "duration": 470, "slot": 4}, {"tid": 64472942, "duration": 292, "slot": 4}, {"tid": 62851106, "duration": 301, "slot": 4}, {"tid": 5645692, "duration": 247, "slot": 4}, {"tid": 63926452, "duration": 242, "slot": 4}, {"tid": 64470586, "duration": 285, "slot": 4}, {"tid": 64070319, "duration": 202, "slot": 4}, {"tid": 64449028, "duration": 287, "slot": 4}, {"tid": 64784398, "duration": 236, "slot": 4}, {"tid": 64007173, "duration": 192, "slot": 4}, {"tid": 63302385, "duration": 121, "slot": 4}, {"tid": 61098600, "duration": 273, "slot": 4}, {"tid": 64898838, "duration": 288, "slot": 4}, {"tid": 63087582, "duration": 269, "slot": 4}, {"tid": 64656063, "duration": 210, "slot": 4}, {"tid": 64542269, "duration": 204, "slot": 4}, {"tid": 64321040, "duration": 144, "slot": 4}]