[{"tid": 6524500, "duration": 287, "slot": 4}, {"tid": 909466, "duration": 270, "slot": 4}, {"tid": 6955350, "duration": 162, "slot": 4}, {"tid": 6971691, "duration": 193, "slot": 4}, {"tid": 15791954, "duration": 294, "slot": 4}, {"tid": 4679081, "duration": 195, "slot": 4}, {"tid": 5478920, "duration": 195, "slot": 4}, {"tid": 1054058, "duration": 211, "slot": 4}, {"tid": 3439522, "duration": 241, "slot": 5}, {"tid": 6961343, "duration": 188, "slot": 5}, {"tid": 3439773, "duration": 247, "slot": 5}, {"tid": 3224145, "duration": 245, "slot": 5}, {"tid": 5754056, "duration": 194, "slot": 5}, {"tid": 13487768, "duration": 201, "slot": 5}, {"tid": 4773336, "duration": 204, "slot": 5}, {"tid": 3437259, "duration": 188, "slot": 5}, {"tid": 6600297, "duration": 263, "slot": 5}, {"tid": 3137619, "duration": 236, "slot": 5}, {"tid": 3257102, "duration": 245, "slot": 5}, {"tid": 573121, "duration": 204, "slot": 5}, {"tid": 3530654, "duration": 247, "slot": 5}, {"tid": 10030273, "duration": 305, "slot": 5}, {"tid": 4679074, "duration": 219, "slot": 5}, {"tid": 8040589, "duration": 138, "slot": 5}, {"tid": 6600302, "duration": 147, "slot": 5}, {"tid": 568139, "duration": 182, "slot": 5}, {"tid": 15747384, "duration": 245, "slot": 5}, {"tid": 7279428, "duration": 227, "slot": 5}, {"tid": 7832461, "duration": 232, "slot": 5}, {"tid": 3437329, "duration": 298, "slot": 5}, {"tid": 3306166, "duration": 335, "slot": 5}, {"tid": 6955857, "duration": 219, "slot": 5}, {"tid": 2331000, "duration": 235, "slot": 5}, {"tid": 5746120, "duration": 202, "slot": 5}, {"tid": 15864048, "duration": 250, "slot": 5}, {"tid": 15426370, "duration": 313, "slot": 5}, {"tid": 545272, "duration": 122, "slot": 5}, {"tid": 6711293, "duration": 262, "slot": 5}, {"tid": 4676900, "duration": 298, "slot": 5}, {"tid": 6161247, "duration": 216, "slot": 5}, {"tid": 1122309, "duration": 282, "slot": 5}, {"tid": 8016112, "duration": 192, "slot": 5}, {"tid": 3224013, "duration": 180, "slot": 5}, {"tid": 1073957, "duration": 203, "slot": 5}, {"tid": 3446846, "duration": 197, "slot": 5}, {"tid": 3285075, "duration": 239, "slot": 5}, {"tid": 1169915, "duration": 235, "slot": 5}, {"tid": 3437247, "duration": 246, "slot": 5}, {"tid": 7832464, "duration": 226, "slot": 5}, {"tid": 3306179, "duration": 347, "slot": 5}]