[{"tid": 4681868, "duration": 217, "slot": 3}, {"tid": 3425474, "duration": 181, "slot": 3}, {"tid": 3872792, "duration": 181, "slot": 3}, {"tid": 2600176, "duration": 236, "slot": 3}, {"tid": 4675515, "duration": 270, "slot": 3}, {"tid": 4103671, "duration": 187, "slot": 3}, {"tid": 11058960, "duration": 189, "slot": 3}, {"tid": 2237179, "duration": 160, "slot": 3}, {"tid": 5642436, "duration": 185, "slot": 3}, {"tid": 41625991, "duration": 183, "slot": 3}, {"tid": 3255778, "duration": 298, "slot": 3}, {"tid": 16472509, "duration": 166, "slot": 3}, {"tid": 3420908, "duration": 205, "slot": 3}, {"tid": 542239, "duration": 144, "slot": 3}, {"tid": 13249157, "duration": 205, "slot": 3}, {"tid": 2253798, "duration": 173, "slot": 3}, {"tid": 3421599, "duration": 157, "slot": 3}, {"tid": 4673921, "duration": 193, "slot": 4}, {"tid": 3202550, "duration": 183, "slot": 4}, {"tid": 3212883, "duration": 140, "slot": 4}, {"tid": 4103660, "duration": 283, "slot": 4}, {"tid": 3442919, "duration": 172, "slot": 4}, {"tid": 2963278, "duration": 235, "slot": 4}, {"tid": 11200205, "duration": 305, "slot": 4}, {"tid": 14549577, "duration": 234, "slot": 4}, {"tid": 17135466, "duration": 197, "slot": 4}, {"tid": 3450959, "duration": 165, "slot": 4}, {"tid": 17371171, "duration": 124, "slot": 4}, {"tid": 3411518, "duration": 128, "slot": 4}, {"tid": 3452599, "duration": 126, "slot": 4}, {"tid": 3576482, "duration": 300, "slot": 4}, {"tid": 3255768, "duration": 235, "slot": 4}, {"tid": 4675515, "duration": 270, "slot": 4}, {"tid": 4669220, "duration": 154, "slot": 4}, {"tid": 24946581, "duration": 190, "slot": 4}, {"tid": 3420908, "duration": 205, "slot": 4}, {"tid": 10985184, "duration": 247, "slot": 4}, {"tid": 3425474, "duration": 181, "slot": 4}, {"tid": 16093568, "duration": 160, "slot": 4}, {"tid": 18112040, "duration": 193, "slot": 4}, {"tid": 638833, "duration": 189, "slot": 4}, {"tid": 3212891, "duration": 169, "slot": 4}, {"tid": 13243979, "duration": 120, "slot": 4}, {"tid": 11058960, "duration": 189, "slot": 4}, {"tid": 2237179, "duration": 160, "slot": 4}, {"tid": 5642436, "duration": 185, "slot": 4}, {"tid": 16208734, "duration": 225, "slot": 4}, {"tid": 3068758, "duration": 247, "slot": 4}, {"tid": 3202550, "duration": 183, "slot": 4}, {"tid": 1741509, "duration": 225, "slot": 4}]