[{"tid": 558617, "duration": 272, "slot": 3}, {"tid": 4193278, "duration": 200, "slot": 3}, {"tid": 6487211, "duration": 337, "slot": 3}, {"tid": 2320549, "duration": 248, "slot": 3}, {"tid": 1112816, "duration": 205, "slot": 3}, {"tid": 1126486, "duration": 165, "slot": 3}, {"tid": 705846, "duration": 0, "slot": 3}, {"tid": 748436, "duration": 288, "slot": 3}, {"tid": 948578, "duration": 316, "slot": 3}, {"tid": 12803377, "duration": 231, "slot": 3}, {"tid": 581923, "duration": 208, "slot": 3}, {"tid": 2963444, "duration": 165, "slot": 3}, {"tid": 1156580, "duration": 344, "slot": 3}, {"tid": 685101, "duration": 340, "slot": 3}, {"tid": 912267, "duration": 331, "slot": 4}, {"tid": 5778168, "duration": 188, "slot": 4}, {"tid": 945378, "duration": 173, "slot": 4}, {"tid": 4315317, "duration": 176, "slot": 4}, {"tid": 922294, "duration": 217, "slot": 4}, {"tid": 12802936, "duration": 221, "slot": 4}, {"tid": 2426862, "duration": 200, "slot": 4}, {"tid": 929147, "duration": 158, "slot": 4}, {"tid": 2925396, "duration": 221, "slot": 4}, {"tid": 6514364, "duration": 243, "slot": 4}, {"tid": 7410264, "duration": 254, "slot": 4}, {"tid": 1175078, "duration": 324, "slot": 4}, {"tid": 2320338, "duration": 193, "slot": 4}, {"tid": 582199, "duration": 271, "slot": 4}, {"tid": 1126486, "duration": 165, "slot": 4}, {"tid": 2320549, "duration": 248, "slot": 4}, {"tid": 936879, "duration": 201, "slot": 4}, {"tid": 936728, "duration": 224, "slot": 4}, {"tid": 598671, "duration": 214, "slot": 4}, {"tid": 1319986, "duration": 261, "slot": 4}, {"tid": 4193278, "duration": 200, "slot": 4}, {"tid": 3168489, "duration": 204, "slot": 4}, {"tid": 685101, "duration": 340, "slot": 4}, {"tid": 4636644, "duration": 242, "slot": 4}, {"tid": 748436, "duration": 288, "slot": 4}, {"tid": 4315310, "duration": 174, "slot": 4}, {"tid": 536398, "duration": 186, "slot": 4}, {"tid": 1156580, "duration": 344, "slot": 4}, {"tid": 3495330, "duration": 215, "slot": 4}, {"tid": 3146785, "duration": 232, "slot": 4}, {"tid": 12802936, "duration": 221, "slot": 4}, {"tid": 4879434, "duration": 240, "slot": 4}, {"tid": 769602, "duration": 249, "slot": 4}, {"tid": 3113980, "duration": 375, "slot": 4}, {"tid": 909557, "duration": 222, "slot": 4}, {"tid": 1177222, "duration": 219, "slot": 4}]