[{"tid": 13178377, "duration": 252, "slot": 3}, {"tid": 3133740, "duration": 238, "slot": 3}, {"tid": 3588300, "duration": 261, "slot": 3}, {"tid": 905131, "duration": 126, "slot": 3}, {"tid": 3420982, "duration": 245, "slot": 3}, {"tid": 720300, "duration": 219, "slot": 3}, {"tid": 5433674, "duration": 266, "slot": 3}, {"tid": 13178380, "duration": 290, "slot": 3}, {"tid": 7297138, "duration": 249, "slot": 3}, {"tid": 9943167, "duration": 200, "slot": 3}, {"tid": 14272852, "duration": 274, "slot": 3}, {"tid": 14348188, "duration": 243, "slot": 3}, {"tid": 2202906, "duration": 140, "slot": 3}, {"tid": 1124124, "duration": 272, "slot": 3}, {"tid": 14309709, "duration": 192, "slot": 4}, {"tid": 13768847, "duration": 137, "slot": 4}, {"tid": 1576747, "duration": 178, "slot": 4}, {"tid": 3113197, "duration": 57, "slot": 4}, {"tid": 7163214, "duration": 216, "slot": 4}, {"tid": 3588301, "duration": 255, "slot": 4}, {"tid": 572299, "duration": 220, "slot": 4}, {"tid": 2451271, "duration": 289, "slot": 4}, {"tid": 3526846, "duration": 201, "slot": 4}, {"tid": 585841, "duration": 178, "slot": 4}, {"tid": 14930475, "duration": 202, "slot": 4}, {"tid": 585871, "duration": 222, "slot": 4}, {"tid": 2261792, "duration": 306, "slot": 4}, {"tid": 2232021, "duration": 223, "slot": 4}, {"tid": 3205696, "duration": 116, "slot": 4}, {"tid": 14142545, "duration": 222, "slot": 4}, {"tid": 5433669, "duration": 272, "slot": 4}, {"tid": 1970019, "duration": 184, "slot": 4}, {"tid": 13178383, "duration": 281, "slot": 4}, {"tid": 14501445, "duration": 238, "slot": 4}, {"tid": 13178377, "duration": 252, "slot": 4}, {"tid": 3133740, "duration": 238, "slot": 4}, {"tid": 13947014, "duration": 141, "slot": 4}, {"tid": 3205712, "duration": 206, "slot": 4}, {"tid": 4765764, "duration": 208, "slot": 4}, {"tid": 7297138, "duration": 249, "slot": 4}, {"tid": 7163214, "duration": 216, "slot": 4}, {"tid": 3143797, "duration": 215, "slot": 4}, {"tid": 14172476, "duration": 206, "slot": 4}, {"tid": 3113197, "duration": 57, "slot": 4}, {"tid": 3205734, "duration": 106, "slot": 4}, {"tid": 14930475, "duration": 202, "slot": 4}, {"tid": 2182616, "duration": 235, "slot": 4}, {"tid": 619369, "duration": 241, "slot": 4}, {"tid": 1576753, "duration": 208, "slot": 4}, {"tid": 14525088, "duration": 407, "slot": 4}]