[{"tid": 62245331, "duration": 209, "slot": 3}, {"tid": 63080448, "duration": 297, "slot": 3}, {"tid": 734432, "duration": 0, "slot": 3}, {"tid": 64669257, "duration": 355, "slot": 3}, {"tid": 64903867, "duration": 294, "slot": 3}, {"tid": 970667, "duration": 294, "slot": 3}, {"tid": 64512257, "duration": 179, "slot": 3}, {"tid": 63117088, "duration": 228, "slot": 3}, {"tid": 64971287, "duration": 289, "slot": 3}, {"tid": 64321040, "duration": 144, "slot": 3}, {"tid": 65364293, "duration": 226, "slot": 3}, {"tid": 4622110, "duration": 258, "slot": 3}, {"tid": 64633887, "duration": 156, "slot": 3}, {"tid": 64783794, "duration": 181, "slot": 3}, {"tid": 64465706, "duration": 337, "slot": 4}, {"tid": 64920073, "duration": 213, "slot": 4}, {"tid": 10545933, "duration": 185, "slot": 4}, {"tid": 65121012, "duration": 180, "slot": 4}, {"tid": 58371941, "duration": 190, "slot": 4}, {"tid": 1012664, "duration": 249, "slot": 4}, {"tid": 64633883, "duration": 165, "slot": 4}, {"tid": 64898838, "duration": 288, "slot": 4}, {"tid": 64669257, "duration": 355, "slot": 4}, {"tid": 63453320, "duration": 202, "slot": 4}, {"tid": 64903867, "duration": 294, "slot": 4}, {"tid": 734432, "duration": 0, "slot": 4}, {"tid": 64593669, "duration": 263, "slot": 4}, {"tid": 64085574, "duration": 217, "slot": 4}, {"tid": 62121610, "duration": 310, "slot": 4}, {"tid": 970667, "duration": 294, "slot": 4}, {"tid": 64321040, "duration": 144, "slot": 4}, {"tid": 64544392, "duration": 287, "slot": 4}, {"tid": 65151284, "duration": 236, "slot": 4}, {"tid": 65021324, "duration": 266, "slot": 4}, {"tid": 65121012, "duration": 180, "slot": 4}, {"tid": 10545933, "duration": 185, "slot": 4}, {"tid": 63189421, "duration": 227, "slot": 4}, {"tid": 64898838, "duration": 288, "slot": 4}, {"tid": 58371951, "duration": 211, "slot": 4}, {"tid": 1012664, "duration": 249, "slot": 4}, {"tid": 63117088, "duration": 228, "slot": 4}, {"tid": 64669257, "duration": 355, "slot": 4}, {"tid": 63453320, "duration": 202, "slot": 4}, {"tid": 63065461, "duration": 510, "slot": 4}, {"tid": 871278, "duration": 236, "slot": 4}, {"tid": 64512257, "duration": 179, "slot": 4}, {"tid": 62730577, "duration": 171, "slot": 4}, {"tid": 1013991, "duration": 216, "slot": 4}, {"tid": 64971287, "duration": 289, "slot": 4}, {"tid": 58371941, "duration": 190, "slot": 4}]