[{"tid": 62131201, "duration": 221, "slot": 3}, {"tid": 55306621, "duration": 122, "slot": 3}, {"tid": 58075991, "duration": 234, "slot": 3}, {"tid": 62234824, "duration": 233, "slot": 3}, {"tid": 16758831, "duration": 230, "slot": 3}, {"tid": 44300721, "duration": 201, "slot": 3}, {"tid": 55969571, "duration": 253, "slot": 3}, {"tid": 61307497, "duration": 219, "slot": 3}, {"tid": 5351602, "duration": 276, "slot": 3}, {"tid": 18196987, "duration": 207, "slot": 3}, {"tid": 61341497, "duration": 205, "slot": 3}, {"tid": 29682701, "duration": 194, "slot": 3}, {"tid": 60815551, "duration": 203, "slot": 3}, {"tid": 41727241, "duration": 241, "slot": 3}, {"tid": 61142530, "duration": 275, "slot": 4}, {"tid": 61531377, "duration": 190, "slot": 4}, {"tid": 36078301, "duration": 330, "slot": 4}, {"tid": 60726278, "duration": 219, "slot": 4}, {"tid": 55829181, "duration": 193, "slot": 4}, {"tid": 17665358, "duration": 254, "slot": 4}, {"tid": 59054001, "duration": 171, "slot": 4}, {"tid": 51485561, "duration": 177, "slot": 4}, {"tid": 15407041, "duration": 242, "slot": 4}, {"tid": 38999231, "duration": 155, "slot": 4}, {"tid": 61179068, "duration": 213, "slot": 4}, {"tid": 59506651, "duration": 216, "slot": 4}, {"tid": 62131201, "duration": 221, "slot": 4}, {"tid": 12817930, "duration": 280, "slot": 4}, {"tid": 57265471, "duration": 204, "slot": 4}, {"tid": 61228591, "duration": 212, "slot": 4}, {"tid": 45461611, "duration": 242, "slot": 4}, {"tid": 52265971, "duration": 226, "slot": 4}, {"tid": 60952625, "duration": 326, "slot": 4}, {"tid": 61108942, "duration": 282, "slot": 4}, {"tid": 40490681, "duration": 236, "slot": 4}, {"tid": 16935920, "duration": 144, "slot": 4}, {"tid": 5351602, "duration": 276, "slot": 4}, {"tid": 25006781, "duration": 227, "slot": 4}, {"tid": 55015251, "duration": 161, "slot": 4}, {"tid": 36951331, "duration": 250, "slot": 4}, {"tid": 15407041, "duration": 242, "slot": 4}, {"tid": 45175201, "duration": 190, "slot": 4}, {"tid": 61391686, "duration": 227, "slot": 4}, {"tid": 16758831, "duration": 230, "slot": 4}, {"tid": 15425735, "duration": 245, "slot": 4}, {"tid": 61142161, "duration": 217, "slot": 4}, {"tid": 59054001, "duration": 171, "slot": 4}, {"tid": 56893231, "duration": 235, "slot": 4}, {"tid": 28541421, "duration": 237, "slot": 4}, {"tid": 62131201, "duration": 221, "slot": 4}]