[{"tid": 11159503, "duration": 282, "slot": 3}, {"tid": 60395521, "duration": 191, "slot": 3}, {"tid": 971637, "duration": 252, "slot": 3}, {"tid": 971639, "duration": 201, "slot": 3}, {"tid": 60869437, "duration": 191, "slot": 3}, {"tid": 52626471, "duration": 276, "slot": 3}, {"tid": 13158541, "duration": 492, "slot": 3}, {"tid": 14373904, "duration": 248, "slot": 3}, {"tid": 12266885, "duration": 202, "slot": 3}, {"tid": 16479472, "duration": 313, "slot": 3}, {"tid": 56902011, "duration": 243, "slot": 3}, {"tid": 17011981, "duration": 237, "slot": 3}, {"tid": 632330, "duration": 306, "slot": 3}, {"tid": 56901991, "duration": 155, "slot": 4}, {"tid": 1099287, "duration": 172, "slot": 4}, {"tid": 4571774, "duration": 300, "slot": 4}, {"tid": 14373908, "duration": 202, "slot": 4}, {"tid": 12266883, "duration": 203, "slot": 4}, {"tid": 3962672, "duration": 315, "slot": 4}, {"tid": 11131733, "duration": 400, "slot": 4}, {"tid": 56902041, "duration": 228, "slot": 4}, {"tid": 1008510, "duration": 214, "slot": 4}, {"tid": 16479473, "duration": 293, "slot": 4}, {"tid": 43462151, "duration": 184, "slot": 4}, {"tid": 61226609, "duration": 187, "slot": 4}, {"tid": 15972659, "duration": 153, "slot": 4}, {"tid": 60395511, "duration": 284, "slot": 4}, {"tid": 43462191, "duration": 189, "slot": 4}, {"tid": 60395521, "duration": 191, "slot": 4}, {"tid": 4571780, "duration": 230, "slot": 4}, {"tid": 17011977, "duration": 254, "slot": 4}, {"tid": 4571779, "duration": 260, "slot": 4}, {"tid": 13738407, "duration": 320, "slot": 4}, {"tid": 13738404, "duration": 274, "slot": 4}, {"tid": 1099291, "duration": 197, "slot": 4}, {"tid": 13533755, "duration": 292, "slot": 4}, {"tid": 60869435, "duration": 131, "slot": 4}, {"tid": 16691969, "duration": 308, "slot": 4}, {"tid": 57278271, "duration": 262, "slot": 4}, {"tid": 1008598, "duration": 251, "slot": 4}, {"tid": 1008510, "duration": 214, "slot": 4}, {"tid": 12342219, "duration": 233, "slot": 4}, {"tid": 12342204, "duration": 244, "slot": 4}, {"tid": 10794584, "duration": 191, "slot": 4}, {"tid": 56902021, "duration": 264, "slot": 4}, {"tid": 11131735, "duration": 358, "slot": 4}, {"tid": 15972659, "duration": 153, "slot": 4}, {"tid": 56902031, "duration": 275, "slot": 4}, {"tid": 17011981, "duration": 237, "slot": 4}, {"tid": 4571780, "duration": 230, "slot": 4}]