[{"tid": 18071176, "duration": 265, "slot": 3}, {"tid": 57230061, "duration": 194, "slot": 3}, {"tid": 18071175, "duration": 163, "slot": 3}, {"tid": 16628936, "duration": 328, "slot": 3}, {"tid": 6302701, "duration": 259, "slot": 3}, {"tid": 16628933, "duration": 197, "slot": 3}, {"tid": 9848604, "duration": 190, "slot": 3}, {"tid": 23378571, "duration": 210, "slot": 3}, {"tid": 3581086, "duration": 232, "slot": 3}, {"tid": 664502, "duration": 256, "slot": 3}, {"tid": 1151563, "duration": 175, "slot": 3}, {"tid": 18071171, "duration": 206, "slot": 3}, {"tid": 1151530, "duration": 240, "slot": 3}, {"tid": 14151548, "duration": 298, "slot": 3}, {"tid": 30320161, "duration": 239, "slot": 3}, {"tid": 15972659, "duration": 153, "slot": 4}, {"tid": 684689, "duration": 212, "slot": 4}, {"tid": 15972657, "duration": 191, "slot": 4}, {"tid": 2947110, "duration": 213, "slot": 4}, {"tid": 3784759, "duration": 244, "slot": 4}, {"tid": 16992777, "duration": 299, "slot": 4}, {"tid": 27098071, "duration": 215, "slot": 4}, {"tid": 15972658, "duration": 152, "slot": 4}, {"tid": 3855823, "duration": 160, "slot": 4}, {"tid": 16628931, "duration": 196, "slot": 4}, {"tid": 18071176, "duration": 265, "slot": 4}, {"tid": 2947109, "duration": 276, "slot": 4}, {"tid": 16992776, "duration": 353, "slot": 4}, {"tid": 3855821, "duration": 225, "slot": 4}, {"tid": 1151534, "duration": 191, "slot": 4}, {"tid": 941948, "duration": 155, "slot": 4}, {"tid": 941912, "duration": 142, "slot": 4}, {"tid": 6302701, "duration": 259, "slot": 4}, {"tid": 16628936, "duration": 328, "slot": 4}, {"tid": 3581086, "duration": 232, "slot": 4}, {"tid": 8209632, "duration": 397, "slot": 4}, {"tid": 14151548, "duration": 298, "slot": 4}, {"tid": 57230051, "duration": 266, "slot": 4}, {"tid": 27099561, "duration": 201, "slot": 4}, {"tid": 3784759, "duration": 244, "slot": 4}, {"tid": 664502, "duration": 256, "slot": 4}, {"tid": 3784757, "duration": 248, "slot": 4}, {"tid": 30320161, "duration": 239, "slot": 4}, {"tid": 15483890, "duration": 323, "slot": 4}, {"tid": 18071171, "duration": 206, "slot": 4}, {"tid": 7439319, "duration": 344, "slot": 4}, {"tid": 14148262, "duration": 229, "slot": 4}, {"tid": 1151563, "duration": 175, "slot": 4}, {"tid": 16992777, "duration": 299, "slot": 4}, {"tid": 15972657, "duration": 191, "slot": 4}]