[{"tid": 16653176, "duration": 429, "slot": 3}, {"tid": 38349941, "duration": 400, "slot": 3}, {"tid": 57272471, "duration": 289, "slot": 3}, {"tid": 13950182, "duration": 333, "slot": 3}, {"tid": 14285430, "duration": 353, "slot": 3}, {"tid": 36582071, "duration": 206, "slot": 3}, {"tid": 34948061, "duration": 332, "slot": 3}, {"tid": 16625691, "duration": 141, "slot": 3}, {"tid": 16625694, "duration": 262, "slot": 3}, {"tid": 11295825, "duration": 424, "slot": 3}, {"tid": 8081249, "duration": 260, "slot": 4}, {"tid": 12680228, "duration": 289, "slot": 4}, {"tid": 62602903, "duration": 195, "slot": 4}, {"tid": 13172153, "duration": 342, "slot": 4}, {"tid": 5896020, "duration": 304, "slot": 4}, {"tid": 16155580, "duration": 280, "slot": 4}, {"tid": 16653176, "duration": 429, "slot": 4}, {"tid": 61419499, "duration": 217, "slot": 4}, {"tid": 46285181, "duration": 372, "slot": 4}, {"tid": 7863647, "duration": 361, "slot": 4}, {"tid": 17099722, "duration": 222, "slot": 4}, {"tid": 53905721, "duration": 374, "slot": 4}, {"tid": 14285430, "duration": 353, "slot": 4}, {"tid": 13172150, "duration": 245, "slot": 4}, {"tid": 8081237, "duration": 251, "slot": 4}, {"tid": 12292191, "duration": 218, "slot": 4}, {"tid": 34812351, "duration": 341, "slot": 4}, {"tid": 57305431, "duration": 588, "slot": 4}, {"tid": 40610321, "duration": 282, "slot": 4}, {"tid": 13053072, "duration": 335, "slot": 4}, {"tid": 34541001, "duration": 425, "slot": 4}, {"tid": 34948081, "duration": 289, "slot": 4}, {"tid": 16653176, "duration": 429, "slot": 4}, {"tid": 13950182, "duration": 333, "slot": 4}, {"tid": 12292185, "duration": 206, "slot": 4}, {"tid": 18255671, "duration": 370, "slot": 4}, {"tid": 13727961, "duration": 288, "slot": 4}, {"tid": 8081240, "duration": 234, "slot": 4}, {"tid": 8081251, "duration": 201, "slot": 4}, {"tid": 61174623, "duration": 312, "slot": 4}, {"tid": 17390559, "duration": 201, "slot": 4}, {"tid": 34540991, "duration": 472, "slot": 4}, {"tid": 17582895, "duration": 344, "slot": 4}, {"tid": 40610291, "duration": 280, "slot": 4}, {"tid": 25746611, "duration": 245, "slot": 5}, {"tid": 15735712, "duration": 371, "slot": 5}, {"tid": 12292191, "duration": 218, "slot": 5}, {"tid": 3825540, "duration": 266, "slot": 5}, {"tid": 60901819, "duration": 257, "slot": 5}, {"tid": 2713139, "duration": 328, "slot": 5}]