[{"tid": 16976616, "duration": 210, "slot": 3}, {"tid": 63237223, "duration": 147, "slot": 3}, {"tid": 61056311, "duration": 296, "slot": 3}, {"tid": 62264075, "duration": 300, "slot": 3}, {"tid": 62264090, "duration": 227, "slot": 3}, {"tid": 58241681, "duration": 197, "slot": 3}, {"tid": 62650930, "duration": 177, "slot": 3}, {"tid": 16186932, "duration": 273, "slot": 3}, {"tid": 12210088, "duration": 244, "slot": 3}, {"tid": 16160983, "duration": 216, "slot": 3}, {"tid": 16608537, "duration": 248, "slot": 3}, {"tid": 45526061, "duration": 130, "slot": 3}, {"tid": 61008511, "duration": 284, "slot": 3}, {"tid": 41035131, "duration": 173, "slot": 3}, {"tid": 57630641, "duration": 216, "slot": 3}, {"tid": 3105068, "duration": 249, "slot": 4}, {"tid": 13789077, "duration": 347, "slot": 4}, {"tid": 42535191, "duration": 229, "slot": 4}, {"tid": 687712, "duration": 193, "slot": 4}, {"tid": 13787134, "duration": 175, "slot": 4}, {"tid": 14405875, "duration": 228, "slot": 4}, {"tid": 12754261, "duration": 188, "slot": 4}, {"tid": 16834135, "duration": 189, "slot": 4}, {"tid": 60847286, "duration": 234, "slot": 4}, {"tid": 62650930, "duration": 177, "slot": 4}, {"tid": 14932630, "duration": 208, "slot": 4}, {"tid": 61430816, "duration": 273, "slot": 4}, {"tid": 56467521, "duration": 178, "slot": 4}, {"tid": 14245771, "duration": 183, "slot": 4}, {"tid": 61784868, "duration": 185, "slot": 4}, {"tid": 12210088, "duration": 244, "slot": 4}, {"tid": 54617841, "duration": 227, "slot": 4}, {"tid": 61250986, "duration": 244, "slot": 4}, {"tid": 41035131, "duration": 173, "slot": 4}, {"tid": 61008511, "duration": 284, "slot": 4}, {"tid": 54519711, "duration": 207, "slot": 4}, {"tid": 16160983, "duration": 216, "slot": 4}, {"tid": 45526061, "duration": 130, "slot": 4}, {"tid": 61056311, "duration": 296, "slot": 4}, {"tid": 55700491, "duration": 210, "slot": 4}, {"tid": 58241681, "duration": 197, "slot": 4}, {"tid": 12754261, "duration": 188, "slot": 4}, {"tid": 16834135, "duration": 189, "slot": 4}, {"tid": 62264090, "duration": 227, "slot": 4}, {"tid": 57630641, "duration": 216, "slot": 4}, {"tid": 17165508, "duration": 185, "slot": 4}, {"tid": 62650930, "duration": 177, "slot": 4}, {"tid": 687712, "duration": 193, "slot": 4}, {"tid": 60886410, "duration": 181, "slot": 4}, {"tid": 62264075, "duration": 300, "slot": 4}]